IDKLOL/__init__.py
IDKlol-0.1.1.dist-info/METADATA
IDKlol-0.1.1.dist-info/WHEEL
IDKlol-0.1.1.dist-info/top_level.txt
IDKlol-0.1.1.dist-info/RECORD
