Metadata-Version: 2.1
Name: IDKlol
Version: 0.1.1
Summary: test for secret
Home-page: UNKNOWN
Author: Mathyslol
License: UNKNOWN
Platform: UNKNOWN
Classifier: Programming Language :: Python :: 3
Classifier: License :: OSI Approved :: MIT License
Classifier: Operating System :: OS Independent
Requires-Dist: BenBotAsync
Requires-Dist: FortniteAPIAsync
Requires-Dist: aiohttp
Requires-Dist: colorama
Requires-Dist: crayons
Requires-Dist: fortnitepy
Requires-Dist: requests
Requires-Dist: sanic (==21.6.2)
Requires-Dist: uvloop
